review_gui.py
image_labeling_yolo-0.1.2.dist-info/licenses/LICENSE
review/__init__.py
review/canvas_utils.py
review/constants.py
review/controller.py
review/gui_app.py
review/io.py
review/models.py
review/view.py
image_labeling_yolo-0.1.2.dist-info/METADATA
image_labeling_yolo-0.1.2.dist-info/WHEEL
image_labeling_yolo-0.1.2.dist-info/entry_points.txt
image_labeling_yolo-0.1.2.dist-info/top_level.txt
image_labeling_yolo-0.1.2.dist-info/RECORD
