Metadata-Version: 2.4
Name: image-labeling-yolo
Version: 0.1.2
Summary: Tkinter GUI for reviewing and editing YOLO labels.
Author: Mateus Coutinho Marim
License: MIT
Project-URL: Homepage, https://github.com/mateus558/image-labeling-yolo
Project-URL: Issues, https://github.com/mateus558/image-labeling-yolo/issues
Keywords: yolo,labeling,annotation,gui,tkinter
Classifier: Development Status :: 4 - Beta
Classifier: Intended Audience :: Developers
Classifier: License :: OSI Approved :: MIT License
Classifier: Programming Language :: Python
Classifier: Programming Language :: Python :: 3
Classifier: Programming Language :: Python :: 3 :: Only
Classifier: Programming Language :: Python :: 3.9
Classifier: Programming Language :: Python :: 3.10
Classifier: Programming Language :: Python :: 3.11
Classifier: Programming Language :: Python :: 3.12
Classifier: Topic :: Scientific/Engineering :: Image Processing
Classifier: Environment :: X11 Applications
Requires-Python: >=3.9
License-File: LICENSE
Requires-Dist: pillow
Provides-Extra: dev
Requires-Dist: pytest>=7; extra == "dev"
Dynamic: license-file
